hatchery/__init__.py
hatchery/_version.py
hatchery/config.py
hatchery/executor.py
hatchery/helpers.py
hatchery/main.py
hatchery/project.py
hatchery/snippets.py
hatchery/snippets/_version.py.snippet
hatchery/snippets/hatchery.yml.snippet
hatchery/snippets/setup.py.snippet
hatchery-0.4.2.dist-info/DESCRIPTION.rst
hatchery-0.4.2.dist-info/METADATA
hatchery-0.4.2.dist-info/RECORD
hatchery-0.4.2.dist-info/WHEEL
hatchery-0.4.2.dist-info/entry_points.txt
hatchery-0.4.2.dist-info/metadata.json
hatchery-0.4.2.dist-info/top_level.txt
